inspyre_toolbox/__about__.py
inspyre_toolbox/__init__.py
inspyre_toolbox/api_changes.ini
inspyre_toolbox/cli/__init__.py
inspyre_toolbox/cli/ist_bytes_converter/__init__.py
inspyre_toolbox/cli/ist_bytes_converter/arguments.py
inspyre_toolbox/cli/ist_bytes_converter/helpers.py
inspyre_toolbox/common/__init__.py
inspyre_toolbox/common/meta.py
inspyre_toolbox/console_kit/__init__.py
inspyre_toolbox/conversions/__init__.py
inspyre_toolbox/conversions/bytes/__init__.py
inspyre_toolbox/conversions/roman_numerals/__init__.py
inspyre_toolbox/conversions/roman_numerals/errors.py
inspyre_toolbox/core/errors/__init__.py
inspyre_toolbox/core/errors/version.py
inspyre_toolbox/core_helpers/__init__.py
inspyre_toolbox/core_helpers/debugging.py
inspyre_toolbox/core_helpers/logging.py
inspyre_toolbox/docs/conversions/bytes.md
inspyre_toolbox/generations/__init__.py
inspyre_toolbox/humanize/__init__.py
inspyre_toolbox/humanize/errors/__init__.py
inspyre_toolbox/humanize/errors/numerical.py
inspyre_toolbox/live_timer/__init__.py
inspyre_toolbox/live_timer/errors.py
inspyre_toolbox/live_timer/history.py
inspyre_toolbox/log_engine/__init__.py
inspyre_toolbox/proc_man/__init__.py
inspyre_toolbox/proc_man/errors.py
inspyre_toolbox/pypi/__init__.py
inspyre_toolbox/pypi/packages.py
inspyre_toolbox/settings.py
inspyre_toolbox/solve_kit/__init__.py
inspyre_toolbox/spanners/__init__.py
inspyre_toolbox/spanners/span_arg_parse.py
inspyre_toolbox/syntactic_sweets/__init__.py
inspyre_toolbox/syntactic_sweets/properties/__init__.py
inspyre_toolbox/syntactic_sweets/properties/decorators/__init__.py
inspyre_toolbox/syntactic_sweets/properties/decorators/paths.py
inspyre_toolbox/syntactic_sweets/properties/decorators/type_validation.py
inspyre_toolbox/syntactic_sweets/properties/descriptors/__init__.py
inspyre_toolbox/syntactic_sweets/properties/descriptors/errors.py
inspyre_toolbox/sys_man/__init__.py
inspyre_toolbox/version.py
inspyre_toolbox-1.5.3.dist-info/entry_points.txt
inspyre_toolbox-1.5.3.dist-info/LICENSE
inspyre_toolbox-1.5.3.dist-info/METADATA
inspyre_toolbox-1.5.3.dist-info/WHEEL
inspyre_toolbox-1.5.3.dist-info/RECORD
