Metadata-Version: 2.1
Name: inspyre-toolbox
Version: 1.5.3
Summary: A toolbox containing some useful tools for Inspyre Softworks packages. Generally useful to some programmers too.
License: MIT
Keywords: toolbox,timer,commify,strings,elapsed
Author: T Blackstone
Author-email: t.blackstone@inspyre.tech
Requires-Python: >=3.10,<4.0
Classifier: Intended Audience :: Developers
Classifier: License :: OSI Approved :: MIT License
Classifier: Natural Language :: English
Classifier: Operating System :: OS Independent
Classifier: Programming Language :: Python :: 3
Classifier: Programming Language :: Python :: 3.10
Classifier: Programming Language :: Python :: 3.11
Classifier: Programming Language :: Python :: 3.12
Classifier: Programming Language :: Python :: 3 :: Only
Classifier: Programming Language :: Python :: 3.6
Classifier: Programming Language :: Python :: 3.7
Classifier: Programming Language :: Python :: 3.8
Classifier: Programming Language :: Python :: 3.9
Classifier: Topic :: Scientific/Engineering :: Mathematics
Classifier: Topic :: Software Development
Classifier: Topic :: Software Development :: Build Tools
Classifier: Topic :: Software Development :: Libraries :: Python Modules
Classifier: Topic :: Terminals
Classifier: Topic :: Utilities
Requires-Dist: DateTime (>=4.3,<5.0)
Requires-Dist: inflect (>=7.2.1,<8.0.0)
Requires-Dist: inspy-logger (>=3.1.0)
Requires-Dist: inspyred-print (>=1.2.1,<2.0.0)
Requires-Dist: psutil (>=6.0.0,<7.0.0)
Requires-Dist: pypattyrn (>=1.2,<2.0)
Requires-Dist: tqdm (>=4.64.0,<5.0.0)
